dailylog1/__init__.py
dailylog1/cache.py
dailylog1/cli.py
dailylog1/config.py
dailylog1/constants.py
dailylog1/exceptions.py
dailylog1/options.py
dailylog1/py.typed
dailylog1-0.3.0.dist-info/LICENSE
dailylog1-0.3.0.dist-info/METADATA
dailylog1-0.3.0.dist-info/WHEEL
dailylog1-0.3.0.dist-info/entry_points.txt
dailylog1-0.3.0.dist-info/RECORD
