Metadata-Version: 2.1
Name: dailylog1
Version: 0.3.0
Summary: 
Keywords: logging
Author: Quien Sabe
Author-email: qs5779@mail.com
Requires-Python: >=3.10,<4.0
Classifier: Development Status :: 3 - Alpha
Classifier: Operating System :: OS Independent
Classifier: Programming Language :: Python :: 3
Classifier: Programming Language :: Python :: 3.10
Classifier: Programming Language :: Python :: 3.11
Classifier: Programming Language :: Python :: 3.12
Classifier: Programming Language :: Python :: 3.13
Classifier: Programming Language :: Python :: 3 :: Only
Classifier: Typing :: Typed
Requires-Dist: click (>=8.1.0,<9.0.0)
Requires-Dist: loguru (>=0.7.2,<0.8.0)
Requires-Dist: tomli (>=2.0.1,<3.0.0)
Requires-Dist: wtforglib (>=1.0.0,<2.0.0)
